karrio/mappers/eshipper/__init__.py
karrio/mappers/eshipper/mapper.py
karrio/mappers/eshipper/proxy.py
karrio/mappers/eshipper/settings.py
karrio/plugins/eshipper/__init__.py
karrio/providers/eshipper/__init__.py
karrio/providers/eshipper/error.py
karrio/providers/eshipper/metadata.json
karrio/providers/eshipper/rate.py
karrio/providers/eshipper/tracking.py
karrio/providers/eshipper/units.py
karrio/providers/eshipper/utils.py
karrio/providers/eshipper/shipment/__init__.py
karrio/providers/eshipper/shipment/cancel.py
karrio/providers/eshipper/shipment/create.py
karrio/schemas/eshipper/__init__.py
karrio/schemas/eshipper/cancel_request.py
karrio/schemas/eshipper/cancel_response.py
karrio/schemas/eshipper/error_response.py
karrio/schemas/eshipper/pickup_cancel_response.py
karrio/schemas/eshipper/pickup_request.py
karrio/schemas/eshipper/pickup_response.py
karrio/schemas/eshipper/rate_request.py
karrio/schemas/eshipper/rate_response.py
karrio/schemas/eshipper/shipping_request.py
karrio/schemas/eshipper/shipping_response.py
karrio/schemas/eshipper/tracking_request.py
karrio/schemas/eshipper/tracking_response.py
karrio_eshipper-2026.1.4.dist-info/METADATA
karrio_eshipper-2026.1.4.dist-info/WHEEL
karrio_eshipper-2026.1.4.dist-info/entry_points.txt
karrio_eshipper-2026.1.4.dist-info/top_level.txt
karrio_eshipper-2026.1.4.dist-info/RECORD
